{
    "brands": {
      "Apple Watch": "watchos",
      "Polar": "polar",
      "Ring": "Ring",
      "Tesla": "Tesla",
      "Audi connect": "Audi Connect",
      "Medtronic": "Medtronic",
      "GE Healthcare": "GE Healthcare",
      "Baxter": "Baxter",
      "Samsung SmartThings": "Samsung",
      "Siemens": "Siemens",
      "ABB": "ABB",
      "Schneider Electric": "Schneider",
      "Honeywell": "Honeywell",
      "Emerson": "Emerson",
      "Rockwell Automation": "Rockwell",
      "Mitsubishi Electric": "Mitsubishi",
      "Cisco": "Cisco",
      "Ericsson": "Ericsson",
      "MQTT": "MQTT",
      "Bluetooth": "Bluetooth",
      "Wifi": "Wifi",
      "Zigbee": "Zigbee",
      "Mercedes me": "Mercedes ME",
      "Samsung Gear": "Samsung Gear",
      "GE Appliances": "GE APPLIANCES",
      "Wemo": "WEMO",
      "Garmin": "GARMIN",
      "Fanuc": "FANUC",
      "Amazon Echo": "AMAZON ECHO",
      "Arlo": "ARLO",
      "Huawei Watch": "HUAWEI WATCH",
      "Google Nest": "GOOGLE NEST",
      "Ecobee": "ECOBEE",
      "Logitech Harmony": "LOGITECH HARMONY",
      "Intel Retail": "INTEL RETAIL",
      "Philips Hue": "PHILIPS HUE",
      "Bosch Home Connect": "BOSCH HOME CONNECT",
      "Philips Healthcare": "PHILIPS HEALTHCARE",
      "Siemens Healthineers": "SIEMENS HEALTHINEERS",
      "Fitbit": "FITBIT",
      "August Smart Lock": "AUGUST SMART LOCK",
      "LG ThinQ": "LG THINQ",
      "IBM Watson IoT": "IBM WATSON IOT",
      "Xiaomi Mi Band": "XIAOMI MI",
      "BMW ConnectedDrive": "BMW CONNECTEDDRIVE",
      "FordPass": "FORDPASS",
      "GM OnStar": "GM ONSTAR",
      "Toyota Entune": "TOYOTA ENTUNE",
      "Volvo On Call": "VOLVO ON CALL",
      "Zimmer Biomet": "ZIMMER BIOMET",
      "Stryker": "STRYKER",
      "Fresenius Medical Care": "FRESENIUS MEDICAL CARE",
      "Whirlpool": "WHIRLPOOL",
      "KitchenAid": "KITCHENAID",
      "Kenmore": "KENMORE",
      "Siemens City": "SIEMENS CITY",
      "Huawei Smart City": "HUAWEI SMART CITY",
      "Schneider Electric Smart City": "SCHNEIDER ELECTRIC SMART CITY",
      "John Deere": "JOHN DEERE",
      "Trimble Agriculture": "TRIMBLE AGRICULTURE",
      "Valmont Industries": "VALMONT INDUSTRIES",
      "DeLaval": "DELAVAL",
      "Ag Leader Technology": "AG LEADER TECHNOLOGY",
      "Teralytic": "TERALYTIC",
      "Precision Planting": "PRECISION PLANTING",
      "IBM Retail": "IBM RETAIL",
      "Cisco Retail": "CISCO RETAIL",
      "Amazon Go": "AMAZON GO",
      "Samsung Retail": "SAMSUNG RETAIL",
      "Microsoft Retail": "MICROSOFT RETAIL",
      "Honeywell Retail": "HONEYWELL RETAIL",
      "Ethernet": "ethernet"
    }
  }
  